[
{"name": "HELLDIVERS™ 2", "date": "2024-02-08", "price": 39.99, "total_positive": 176435, "total_negative": 23741, "total_reviews": 200176, "review_score": 8, "review_score_desc": "Very Positive"},
{"name": "Supermarket Simulator", "date": "2024-02-20", "price": 12.99, "total_positive": 5296, "total_negative": 269, "total_reviews": 5565, "review_score": 9, "review_score_desc": "Overwhelmingly Positive"},
{"name": "Rust", "date": "2018-02-08", "price": 39.99, "total_positive": 385560, "total_negative": 55426, "total_reviews": 440986, "review_score": 8, "review_score_desc": "Very Positive"},
{"name": "Balatro", "date": "2024-02-20", "price": 14.99, "total_positive": 12665, "total_negative": 264, "total_reviews": 12929, "review_score": 9, "review_score_desc": "Overwhelmingly Positive"},
{"name": "FINAL FANTASY XIV Online", "date": "2014-02-18", "price": 19.99, "total_positive": 45748, "total_negative": 5723, "total_reviews": 51471, "review_score": 8, "review_score_desc": "Very Positive"},
{"name": "Palworld", "date": "2024-01-18", "price": 29.99, "total_positive": 102969, "total_negative": 4855, "total_reviews": 107824, "review_score": 9, "review_score_desc": "Overwhelmingly Positive"},
{"name": "Grand Theft Auto V", "date": "2015-04-13", "price": 59.97, "total_positive": 410794, "total_negative": 85277, "total_reviews": 496071, "review_score": 8, "review_score_desc": "Very Positive"},
{"name": "Last Epoch", "date": "2024-02-21", "price": 34.99, "total_positive": 37774, "total_negative": 7469, "total_reviews": 45243, "review_score": 8, "review_score_desc": "Very Positive"},
{"name": "Lost Ark", "date": "2022-02-11", "price": 0, "total_positive": 27439, "total_negative": 11419, "total_reviews": 38858, "review_score": 6, "review_score_desc": "Mostly Positive"},
{"name": "The Sims™ 4", "date": "2020-06-18", "price": 0, "total_positive": 36476, "total_negative": 4358, "total_reviews": 40834, "review_score": 8, "review_score_desc": "Very Positive"},
{"name": "Enshrouded", "date": "2024-01-24", "price": 29.99, "total_positive": 17826, "total_negative": 2441, "total_reviews": 20267, "review_score": 8, "review_score_desc": "Very Positive"},
{"name": "Destiny 2", "date": "2019-10-01", "price": 0, "total_positive": 58652, "total_negative": 12697, "total_reviews": 71349, "review_score": 8, "review_score_desc": "Very Positive"},
{"name": "War Thunder", "date": "2013-08-15", "price": 0, "total_positive": 513, "total_negative": 231, "total_reviews": 744, "review_score": 5, "review_score_desc": "Mixed"},
{"name": "Stardew Valley", "date": "2016-02-26", "price": 14.99, "total_positive": 283564, "total_negative": 3234, "total_reviews": 286798, "review_score": 9, "review_score_desc": "Overwhelmingly Positive"},
{"name": "Apex Legends™", "date": "2020-11-04", "price": 0, "total_positive": 811, "total_negative": 133, "total_reviews": 944, "review_score": 8, "review_score_desc": "Very Positive"},
{"name": "FINAL FANTASY VII REMAKE INTERGRADE", "date": "2022-06-17", "price": 69.99, "total_positive": 8940, "total_negative": 1267, "total_reviews": 10207, "review_score": 8, "review_score_desc": "Very Positive"},
{"name": "Lethal Company", "date": "2023-10-23", "price": 9.99, "total_positive": 205980, "total_negative": 4469, "total_reviews": 210449, "review_score": 9, "review_score_desc": "Overwhelmingly Positive"},
{"name": "Dead by Daylight", "date": "2016-06-14", "price": 19.99, "total_positive": 157561, "total_negative": 36832, "total_reviews": 194393, "review_score": 8, "review_score_desc": "Very Positive"},
{"name": "Warframe", "date": "2013-03-25", "price": 0, "total_positive": 986, "total_negative": 136, "total_reviews": 1122, "review_score": 8, "review_score_desc": "Very Positive"},
{"name": "ELDEN RING", "date": "2022-02-24", "price": 59.99, "total_positive": 294218, "total_negative": 19693, "total_reviews": 313911, "review_score": 8, "review_score_desc": "Very Positive"},
{"name": "Horizon Forbidden West™ Complete Edition", "date": "2024-03-21", "price": 59.99, "total_positive": 1467, "total_negative": 94, "total_reviews": 1561, "review_score": 8, "review_score_desc": "Very Positive"},
{"name": "Dragon's Dogma 2", "date": "2024-03-21", "price": 69.99, "total_positive": 12117, "total_negative": 8389, "total_reviews": 20506, "review_score": 5, "review_score_desc": "Mixed"},
{"name": "Tom Clancy's Rainbow Six® Siege", "date": "2015-12-01", "price": 19.99, "total_positive": 440323, "total_negative": 70488, "total_reviews": 510811, "review_score": 8, "review_score_desc": "Very Positive"},
{"name": "Baldur's Gate 3", "date": "2023-08-03", "price": 59.99, "total_positive": 315560, "total_negative": 10550, "total_reviews": 326110, "review_score": 9, "review_score_desc": "Overwhelmingly Positive"},
{"name": "Counter-Strike 2", "date": "2012-08-21", "price": 0, "total_positive": 1069366, "total_negative": 155056, "total_reviews": 1224422, "review_score": 8, "review_score_desc": "Very Positive"}
]